{"url":"https://apiw.infoimoveis.com.br/imoveis/672919","body":"{\n    \"success\": true,\n    \"message\": \"Detalhes do imóvel\",\n    \"data\": {\n        \"id\": 672919,\n        \"titulo\": \"Casa próxima do Bosque da Paz\",\n        \"endereco\": \"R. Mario de Andrade, 305\",\n        \"valor\": 3200,\n        \"finalidade\": \"Aluguel\",\n        \"tipo\": \"Casa-Térrea\",\n        \"cidade\": \"Campo Grande\",\n        \"bairro\": \"Vila do Polonês\",\n        \"estado\": \"MS\",\n        \"dormitorios\": 3,\n        \"banheiros\": 3,\n        \"garagem\": 2,\n        \"area_total\": \"105,00\",\n        \"area_construida\": \"105,00\",\n        \"valor_m2\": 0,\n        \"destaque\": false,\n        \"destaque_lista\": false,\n        \"lancamento\": false,\n        \"favorito\": false,\n        \"informacoes\": \"1 área de serviço coberta, 1 WC empregada, 1 varanda com churrasqueira, 2 garagens, 1 apartamento com armário embutido, 1 WC social, 1 quarto, 1 cozinha com armário embutido, 1 sala de estar para 2 ambientes, 1 quarto com armário embutido.\",\n        \"observacoes\": \"Valores de IPTU e condomínio sujeitos à alteração. As modalidades de garantia aceitas são: fiador, seguro fiança locatícia e título de capitalização.\",\n        \"iptu\": \"R$ 181,34\",\n        \"latitude\": \"-20.439271\",\n        \"longitude\": \"-54.578300\",\n        \"imagens\": [\n            {\n                \"imagem\": \"1773858797_78335.jpg\",\n                \"legenda\": \"Fachada frontal\"\n            },\n            {\n                \"imagem\": \"1773858797_86981.jpg\",\n                \"legenda\": \"\"\n            },\n            {\n                \"imagem\": \"1773858797_94744.jpg\",\n                \"legenda\": \"\"\n            },\n            {\n                \"imagem\": \"1773858798_02635.jpg\",\n                \"legenda\": \"\"\n            },\n            {\n                \"imagem\": \"1773858798_10352.jpg\",\n                \"legenda\": \"\"\n            },\n            {\n                \"imagem\": \"1773858798_17568.jpg\",\n                \"legenda\": \"\"\n            },\n            {\n                \"imagem\": \"1773858798_24664.jpg\",\n                \"legenda\": \"\"\n            },\n            {\n                \"imagem\": \"1773858798_31796.jpg\",\n                \"legenda\": \"\"\n            },\n            {\n                \"imagem\": \"1773858798_39041.jpg\",\n                \"legenda\": \"\"\n            },\n            {\n                \"imagem\": \"1773858798_46009.jpg\",\n                \"legenda\": \"\"\n            },\n            {\n                \"imagem\": \"1773858798_53015.jpg\",\n                \"legenda\": \"\"\n            },\n            {\n                \"imagem\": \"1773858798_60172.jpg\",\n                \"legenda\": \"\"\n            },\n            {\n                \"imagem\": \"1773858798_67448.jpg\",\n                \"legenda\": \"\"\n            },\n            {\n                \"imagem\": \"1773858798_74670.jpg\",\n                \"legenda\": \"\"\n            },\n            {\n                \"imagem\": \"1773858798_81749.jpg\",\n                \"legenda\": \"\"\n            },\n            {\n                \"imagem\": \"1773858798_88751.jpg\",\n                \"legenda\": \"\"\n            },\n            {\n                \"imagem\": \"1773858798_95690.jpg\",\n                \"legenda\": \"\"\n            },\n            {\n                \"imagem\": \"1773858799_02709.jpg\",\n                \"legenda\": \"\"\n            },\n            {\n                \"imagem\": \"1773858799_09644.jpg\",\n                \"legenda\": \"\"\n            },\n            {\n                \"imagem\": \"1773858799_16752.jpg\",\n                \"legenda\": \"\"\n            },\n            {\n                \"imagem\": \"1773858799_23961.jpg\",\n                \"legenda\": \"\"\n            },\n            {\n                \"imagem\": \"1773858799_31047.jpg\",\n                \"legenda\": \"\"\n            },\n            {\n                \"imagem\": \"1773858799_37962.jpg\",\n                \"legenda\": \"\"\n            },\n            {\n                \"imagem\": \"1773858799_45055.jpg\",\n                \"legenda\": \"\"\n            }\n        ],\n        \"planta_baixa\": \"\",\n        \"fotos_condominio\": [],\n        \"caracteristicas\": [\n            \"1 Apto(s) com a\\/e\",\n            \"1 Quarto(s) com a\\/e\",\n            \"1 Quarto(s)\",\n            \"1 Sala de estar\",\n            \"1 Sala de jantar\",\n            \"1 Varanda\",\n            \"1 Wc social\",\n            \"2 Vaga(s) de garagem\",\n            \"WC de serviço\",\n            \"Cozinha planejada\",\n            \"Área de serviço\",\n            \"Churrasqueira\"\n        ],\n        \"infraestrutura\": [],\n        \"anunciante\": {\n            \"id\": 27,\n            \"nome\": \"Financial Imobiliária\",\n            \"creci\": \"699-J\",\n            \"endereco\": \"Rua Hélio Yoshiaki Ikieziri, 34 - loja 01\",\n            \"bairro\": \"Royal Park\",\n            \"cidade\": \"Campo Grande \\/ MS\",\n            \"site\": \"https:\\/\\/financialimobiliaria.com.br\",\n            \"latitude\": \"-20.457294\",\n            \"longitude\": \"-54.583282\",\n            \"imagem\": \"stored\\/imobiliarias\\/1767817331_91772.jpg\",\n            \"tipo\": \"imobiliaria\",\n            \"desde\": \"06\\/2005\",\n            \"total_imoveis\": \"178\"\n        },\n        \"seo\": {\n            \"title\": \"Casa-Térrea para Alugar em Vila do Polonês, Campo Grande MS - 672919 - InfoImóveis\",\n            \"description\": \"Casa-Térrea para alugar em Vila do Polonês, Campo Grande MS com 3 quartos, churrasqueira, cozinha planejada, área de serviço, vaga coberta. Agende sua visita!.\"\n        }\n    }\n}","savedAt":"2026-04-25T18:05:55.954Z"}