{"url":"https://apiw.infoimoveis.com.br/imoveis/663901","body":"{\n    \"success\": true,\n    \"message\": \"Detalhes do imóvel\",\n    \"data\": {\n        \"id\": 663901,\n        \"titulo\": \"Casa moderna com fino acabamento - seminova\",\n        \"endereco\": \"R. José Danilo Pessoa Navarro\",\n        \"valor\": 3100,\n        \"finalidade\": \"Aluguel\",\n        \"tipo\": \"Casa-Térrea\",\n        \"cidade\": \"Campo Grande\",\n        \"bairro\": \"Carandá Bosque III\",\n        \"estado\": \"MS\",\n        \"dormitorios\": 2,\n        \"banheiros\": 3,\n        \"garagem\": 2,\n        \"area_total\": \"150,00\",\n        \"area_construida\": \"119,00\",\n        \"valor_m2\": 0,\n        \"destaque\": false,\n        \"destaque_lista\": false,\n        \"lancamento\": false,\n        \"favorito\": false,\n        \"informacoes\": \"São dois dormitórios com banheiro (tipo suíte), lavabo, sala, cozinha, área de serviço, garagem coberta para dois carros e área de lazer com churrasqueira e pia. Portão de elevação da garagem de veículos com motor elétrico e duas travas de segurança. Portão social com fechadura elétrica e mais trava de segurança com chave tetra, interfone. Lavabo, cozinha com cuba em aço inox, armário planejado e mesa para refeições rápidas. Área de serviço. Janela dos quartos tipo veneziana com grade. Pré-instalação para ar condicionado nos quartos. Banheiros com torneira monocomando, box em vidro temperado, nicho e ducha. Aquecedor solar com água quente nos banheiros e na cozinha.  \",\n        \"iptu\": \"R$ 233,00\",\n        \"imagens\": [\n            {\n                \"imagem\": \"1770131241_73164.jpg\",\n                \"legenda\": \"Fachada frontal\"\n            },\n            {\n                \"imagem\": \"1770131241_80512.jpg\",\n                \"legenda\": \"\"\n            },\n            {\n                \"imagem\": \"1770131241_87833.jpg\",\n                \"legenda\": \"\"\n            },\n            {\n                \"imagem\": \"1770131241_97222.jpg\",\n                \"legenda\": \"\"\n            },\n            {\n                \"imagem\": \"1770131242_04556.jpg\",\n                \"legenda\": \"\"\n            },\n            {\n                \"imagem\": \"1770131242_13921.jpg\",\n                \"legenda\": \"\"\n            },\n            {\n                \"imagem\": \"1770131242_21155.jpg\",\n                \"legenda\": \"\"\n            },\n            {\n                \"imagem\": \"1770131242_30475.jpg\",\n                \"legenda\": \"\"\n            },\n            {\n                \"imagem\": \"1770131242_37641.jpg\",\n                \"legenda\": \"\"\n            },\n            {\n                \"imagem\": \"1770131242_45151.jpg\",\n                \"legenda\": \"\"\n            },\n            {\n                \"imagem\": \"1770131242_54490.jpg\",\n                \"legenda\": \"\"\n            },\n            {\n                \"imagem\": \"1770131242_63898.jpg\",\n                \"legenda\": \"\"\n            },\n            {\n                \"imagem\": \"1770131242_71146.jpg\",\n                \"legenda\": \"\"\n            }\n        ],\n        \"planta_baixa\": \"\",\n        \"fotos_condominio\": [],\n        \"caracteristicas\": [\n            \"2 Suíte(s)\",\n            \"1 Sala de estar\",\n            \"1 Varanda\",\n            \"2 Vaga(s) de garagem\",\n            \"Cozinha planejada\",\n            \"Esgoto\",\n            \"Rede elétrica\",\n            \"Muro\",\n            \"Asfalto\",\n            \"Água\",\n            \"Portão elétrico\",\n            \"Porteiro eletrônico\",\n            \"Interfone\",\n            \"Aquecedor solar\",\n            \"Lavabo\",\n            \"Alarme\",\n            \"Área de serviço\",\n            \"Calçada\"\n        ],\n        \"infraestrutura\": [],\n        \"anunciante\": {\n            \"id\": 553,\n            \"nome\": \"Edmilson Luiz Felipe Alves\",\n            \"creci\": \"4310\",\n            \"endereco\": \"Rua Estrela do Norte, 81\",\n            \"bairro\": \"Carandá Bosque I\",\n            \"cidade\": \"Campo Grande \\/ MS\",\n            \"site\": \"\",\n            \"latitude\": \"\",\n            \"longitude\": \"\",\n            \"imagem\": \"stored\\/corretores\\/1604425683_24393.jpg\",\n            \"tipo\": \"corretor\",\n            \"desde\": \"05\\/2009\",\n            \"total_imoveis\": \"28\"\n        },\n        \"seo\": {\n            \"title\": \"Casa-Térrea para Alugar em Carandá Bosque III, Campo Grande MS - 663901 - InfoImóveis\",\n            \"description\": \"Casa-Térrea para alugar em Carandá Bosque III, Campo Grande MS com 2 quartos, suíte, cozinha planejada, área de serviço, vaga coberta, interfone.\"\n        }\n    }\n}","savedAt":"2026-04-25T18:03:58.968Z"}