{"url":"https://apiw.infoimoveis.com.br/imoveis/663881","body":"{\n    \"success\": true,\n    \"message\": \"Detalhes do imóvel\",\n    \"data\": {\n        \"id\": 663881,\n        \"titulo\": \"Ótima oportunidade - casa no Pedrossian\",\n        \"endereco\": \"\",\n        \"valor\": 2000,\n        \"finalidade\": \"Aluguel\",\n        \"tipo\": \"Casa-Térrea\",\n        \"cidade\": \"Campo Grande\",\n        \"bairro\": \"Maria Aparecida Pedrossian\",\n        \"estado\": \"MS\",\n        \"dormitorios\": 2,\n        \"banheiros\": 3,\n        \"garagem\": 0,\n        \"area_total\": \"200,00\",\n        \"area_construida\": \"52,14\",\n        \"valor_m2\": 0,\n        \"destaque\": false,\n        \"destaque_lista\": false,\n        \"lancamento\": false,\n        \"favorito\": false,\n        \"observacoes\": \"Imóvel em uma região bem localizada, no bairro Maria Aparecida Pedrossian. Agende sua visita.\",\n        \"imagens\": [\n            {\n                \"imagem\": \"1770127905_41813.jpg\",\n                \"legenda\": \"Fachada frontal\"\n            },\n            {\n                \"imagem\": \"1770127905_95450.jpg\",\n                \"legenda\": \"\"\n            },\n            {\n                \"imagem\": \"1770127905_67936.jpg\",\n                \"legenda\": \"\"\n            },\n            {\n                \"imagem\": \"1770127905_27183.jpg\",\n                \"legenda\": \"\"\n            },\n            {\n                \"imagem\": \"1770127905_38375.jpg\",\n                \"legenda\": \"\"\n            },\n            {\n                \"imagem\": \"1770127905_49063.jpg\",\n                \"legenda\": \"\"\n            },\n            {\n                \"imagem\": \"1770127905_33189.jpg\",\n                \"legenda\": \"\"\n            },\n            {\n                \"imagem\": \"1770127905_13075.jpg\",\n                \"legenda\": \"\"\n            },\n            {\n                \"imagem\": \"1770127905_69628.jpg\",\n                \"legenda\": \"\"\n            },\n            {\n                \"imagem\": \"1770127905_83805.jpg\",\n                \"legenda\": \"\"\n            },\n            {\n                \"imagem\": \"1770127905_10204.jpg\",\n                \"legenda\": \"\"\n            },\n            {\n                \"imagem\": \"1770127905_25639.jpg\",\n                \"legenda\": \"\"\n            },\n            {\n                \"imagem\": \"1770127905_62925.jpg\",\n                \"legenda\": \"\"\n            },\n            {\n                \"imagem\": \"1770127905_95953.jpg\",\n                \"legenda\": \"\"\n            },\n            {\n                \"imagem\": \"1770127905_15257.jpg\",\n                \"legenda\": \"\"\n            }\n        ],\n        \"planta_baixa\": \"\",\n        \"fotos_condominio\": [],\n        \"caracteristicas\": [\n            \"2 Quarto(s)\",\n            \"1 Sala de estar\",\n            \"1 Wc social\",\n            \"WC de serviço\",\n            \"Rede elétrica\",\n            \"Muro\",\n            \"Asfalto\",\n            \"Água\",\n            \"Edícula\",\n            \"Despensa\",\n            \"Lavanderia\",\n            \"Lavabo\",\n            \"Área de serviço\",\n            \"Cozinha\",\n            \"Calçada\"\n        ],\n        \"infraestrutura\": [\n            \"Supermercado\",\n            \"Padaria\",\n            \"Farmácia\",\n            \"Escola Estadual\",\n            \"Escola Particular\",\n            \"Praça\",\n            \"Lotérica\",\n            \"Conveniência\",\n            \"Postos de Saúde\",\n            \"Parque\",\n            \"Igreja\",\n            \"Pista de Caminhada\",\n            \"Shopping\",\n            \"Centro Comercial\",\n            \"Feira\",\n            \"Delegacia\",\n            \"Correio\"\n        ],\n        \"anunciante\": {\n            \"id\": 4471,\n            \"nome\": \"Giselle Alves Queiroz\",\n            \"creci\": \"9529\",\n            \"endereco\": \"Rua Filomena Segundo Nascimento, 2574\",\n            \"bairro\": \"Jardim das Perdizes\",\n            \"cidade\": \"Campo Grande \\/ MS\",\n            \"site\": \"\",\n            \"latitude\": \"-20.524541\",\n            \"longitude\": \"-54.585813\",\n            \"imagem\": \"\",\n            \"tipo\": \"corretor\",\n            \"desde\": \"05\\/2024\",\n            \"total_imoveis\": \"30\"\n        },\n        \"seo\": {\n            \"title\": \"Casa-Térrea para Alugar em Maria Aparecida Pedrossian, Campo Grande MS - 663881 - InfoImóveis\",\n            \"description\": \"Casa-Térrea para alugar em Maria Aparecida Pedrossian, Campo Grande MS com 2 quartos, cozinha, área de serviço. Ótima oportunidade - casa no Pedrossian.\"\n        }\n    }\n}","savedAt":"2026-04-25T18:01:44.241Z"}