{"url":"https://apiw.infoimoveis.com.br/imoveis/628242","body":"{\n    \"success\": true,\n    \"message\": \"Detalhes do imóvel\",\n    \"data\": {\n        \"id\": 628242,\n        \"titulo\": \"Casa no Carandá Bosque\",\n        \"endereco\": \"R. Jamil Felix Naglis, 50\",\n        \"valor\": 4500,\n        \"finalidade\": \"Aluguel\",\n        \"tipo\": \"Casa-Térrea\",\n        \"cidade\": \"Campo Grande\",\n        \"bairro\": \"Carandá Bosque I\",\n        \"estado\": \"MS\",\n        \"dormitorios\": 3,\n        \"banheiros\": 4,\n        \"garagem\": 2,\n        \"valor_m2\": 0,\n        \"destaque\": false,\n        \"destaque_lista\": false,\n        \"lancamento\": false,\n        \"favorito\": false,\n        \"informacoes\": \"Duas suítes com guarda-roupas e um quarto com guarda-roupa. Possui um banheiro social e um lavabo, cozinha americana toda planejada com armários e um quintal nos fundos.\",\n        \"observacoes\": \"Garantias para locação: seguro fiança e Loft.\",\n        \"latitude\": \"-20.442527\",\n        \"longitude\": \"-54.568383\",\n        \"imagens\": [\n            {\n                \"imagem\": \"1749065348_01624.jpg\",\n                \"legenda\": \"Fachada frontal\"\n            },\n            {\n                \"imagem\": \"1749065348_05345.jpg\",\n                \"legenda\": \"\"\n            },\n            {\n                \"imagem\": \"1749040765_55234.jpg\",\n                \"legenda\": \"\"\n            },\n            {\n                \"imagem\": \"1749040765_64899.jpg\",\n                \"legenda\": \"\"\n            },\n            {\n                \"imagem\": \"1749040765_74524.jpg\",\n                \"legenda\": \"\"\n            },\n            {\n                \"imagem\": \"1749040765_84395.jpg\",\n                \"legenda\": \"\"\n            },\n            {\n                \"imagem\": \"1749040765_94171.jpg\",\n                \"legenda\": \"\"\n            },\n            {\n                \"imagem\": \"1749040766_03768.jpg\",\n                \"legenda\": \"\"\n            },\n            {\n                \"imagem\": \"1749040766_13266.jpg\",\n                \"legenda\": \"\"\n            },\n            {\n                \"imagem\": \"1749040766_22911.jpg\",\n                \"legenda\": \"\"\n            },\n            {\n                \"imagem\": \"1749040766_32690.jpg\",\n                \"legenda\": \"\"\n            },\n            {\n                \"imagem\": \"1749040766_42261.jpg\",\n                \"legenda\": \"\"\n            },\n            {\n                \"imagem\": \"1749040766_51980.jpg\",\n                \"legenda\": \"\"\n            },\n            {\n                \"imagem\": \"1749040766_61599.jpg\",\n                \"legenda\": \"\"\n            },\n            {\n                \"imagem\": \"1749040766_71430.jpg\",\n                \"legenda\": \"\"\n            },\n            {\n                \"imagem\": \"1749040766_81318.jpg\",\n                \"legenda\": \"\"\n            },\n            {\n                \"imagem\": \"1749040766_91461.jpg\",\n                \"legenda\": \"\"\n            }\n        ],\n        \"planta_baixa\": \"\",\n        \"fotos_condominio\": [],\n        \"caracteristicas\": [\n            \"2 Suíte(s) com a\\/e\",\n            \"1 Quarto(s) com a\\/e\",\n            \"1 Sala de TV\",\n            \"1 Wc social\",\n            \"2 Vaga(s) de garagem\",\n            \"Cozinha\",\n            \"Piso tátil\",\n            \"Imóvel alugado com renda\",\n            \"Cozinha americana\",\n            \"Calçada\",\n            \"Esgoto\",\n            \"Rede elétrica\",\n            \"Muro\",\n            \"Asfalto\",\n            \"Água\",\n            \"Jardim\",\n            \"Lavanderia\",\n            \"Lavabo\",\n            \"Alarme\",\n            \"Área de serviço\",\n            \"Cozinha planejada\",\n            \"WC adaptado\"\n        ],\n        \"infraestrutura\": [\n            \"Supermercado\",\n            \"Padaria\",\n            \"Farmácia\",\n            \"Escola Municipal\",\n            \"Escola Estadual\",\n            \"Escola Particular\",\n            \"Universidade\",\n            \"Praça\",\n            \"Lotérica\",\n            \"Conveniência\",\n            \"Mercado\",\n            \"Hospital\",\n            \"Postos de Saúde\",\n            \"Parque\",\n            \"Igreja\",\n            \"Terminal Rodoviário\",\n            \"Ciclovia\",\n            \"Pista de Caminhada\",\n            \"Shopping\",\n            \"Centro Comercial\",\n            \"Feira\",\n            \"Posto Policial\",\n            \"Delegacia\",\n            \"Clube\",\n            \"Correio\",\n            \"Teatro\",\n            \"Faculdade\"\n        ],\n        \"anunciante\": {\n            \"id\": 2720,\n            \"nome\": \"Issa Negócios Imobiliários\",\n            \"creci\": \"9431-J\",\n            \"endereco\": \"Rua Antônio Maria Coelho, 4110\",\n            \"bairro\": \"Santa Fé\",\n            \"cidade\": \"Campo Grande \\/ MS\",\n            \"site\": \"https:\\/\\/www.jissaimoveis.com.br\",\n            \"latitude\": \"-20.4530659\",\n            \"longitude\": \"-54.5930349\",\n            \"imagem\": \"stored\\/imobiliarias\\/1558991391_55215.jpg\",\n            \"tipo\": \"imobiliaria\",\n            \"desde\": \"11\\/2017\",\n            \"total_imoveis\": \"83\"\n        },\n        \"seo\": {\n            \"title\": \"Casa-Térrea para Alugar em Carandá Bosque I, Campo Grande MS - 628242 - InfoImóveis\",\n            \"description\": \"Casa-Térrea para alugar em Carandá Bosque I, Campo Grande MS com 3 quartos, suíte, cozinha planejada, área de serviço, vaga coberta. Casa no Carandá Bosque.\"\n        }\n    }\n}","savedAt":"2026-04-25T18:06:07.333Z"}